spectral_recovery/__init__.py
spectral_recovery/config.py
spectral_recovery/indices.py
spectral_recovery/metrics.py
spectral_recovery/plotting.py
spectral_recovery/timeseries.py
spectral_recovery/utils.py
spectral_recovery/data/__init__.py
spectral_recovery/data/bc06_wildfire_restoration_site.gpkg
spectral_recovery/data/bc06_wildfire_landsat_BAP/2002.tif
spectral_recovery/data/bc06_wildfire_landsat_BAP/2003.tif
spectral_recovery/data/bc06_wildfire_landsat_BAP/2004.tif
spectral_recovery/data/bc06_wildfire_landsat_BAP/2005.tif
spectral_recovery/data/bc06_wildfire_landsat_BAP/2006.tif
spectral_recovery/data/bc06_wildfire_landsat_BAP/2007.tif
spectral_recovery/data/bc06_wildfire_landsat_BAP/2008.tif
spectral_recovery/data/bc06_wildfire_landsat_BAP/2009.tif
spectral_recovery/data/bc06_wildfire_landsat_BAP/2010.tif
spectral_recovery/data/bc06_wildfire_landsat_BAP/2011.tif
spectral_recovery/data/bc06_wildfire_landsat_BAP/2012.tif
spectral_recovery/data/bc06_wildfire_landsat_BAP/2013.tif
spectral_recovery/data/bc06_wildfire_landsat_BAP/2014.tif
spectral_recovery/data/bc06_wildfire_landsat_BAP/2015.tif
spectral_recovery/data/bc06_wildfire_landsat_BAP/2016.tif
spectral_recovery/data/bc06_wildfire_landsat_BAP/2017.tif
spectral_recovery/data/bc06_wildfire_landsat_BAP/2018.tif
spectral_recovery/data/bc06_wildfire_landsat_BAP/2019.tif
spectral_recovery/data/bc06_wildfire_landsat_BAP/2020.tif
spectral_recovery/data/bc06_wildfire_landsat_BAP/2021.tif
spectral_recovery/data/bc06_wildfire_landsat_BAP/2022.tif
spectral_recovery/data/bc06_wildfire_landsat_BAP/2023.tif
spectral_recovery/io/__init__.py
spectral_recovery/io/polygon.py
spectral_recovery/io/raster.py
spectral_recovery/resources/__init__.py
spectral_recovery/resources/constant_defaults.json
spectral_recovery/targets/__init__.py
spectral_recovery/targets/historic.py
spectral_recovery/targets/reference.py
spectral_recovery-1.0.1.dist-info/LICENSE
spectral_recovery-1.0.1.dist-info/METADATA
spectral_recovery-1.0.1.dist-info/WHEEL
spectral_recovery-1.0.1.dist-info/top_level.txt
spectral_recovery-1.0.1.dist-info/RECORD
