Metadata-Version: 2.1
Name: spectral_recovery
Version: 1.0.1
Author-email: Sarah Zwiep <sarahvz@mail.ubc.ca>
Maintainer-email: Sarah Zwiep <sarahvz@mail.ubc.ca>
License: Apache License
Classifier: Development Status :: 4 - Beta
Classifier: Programming Language :: Python
Requires-Python: >=3.10
License-File: LICENSE
Requires-Dist: geopandas >=0.13.2
Requires-Dist: rioxarray >=0.14.1
Requires-Dist: rasterio >=1.3.7
Requires-Dist: xarray >=2023.5.0
Requires-Dist: spyndex ==0.5.0
Requires-Dist: numpy >=1.24.3
Requires-Dist: dask >=2023.5.1
Requires-Dist: distributed >=2023.5.1
Requires-Dist: dask-expr >=1.0
Requires-Dist: matplotlib >=3.7.1
Requires-Dist: seaborn >=0.12.2
Provides-Extra: docs
Requires-Dist: mkdocs ~=1.5.3 ; extra == 'docs'
Requires-Dist: mkdocs-material ~=9.5.18 ; extra == 'docs'
Requires-Dist: mkdocstrings-python ~=1.9.2 ; extra == 'docs'
Provides-Extra: lint
Requires-Dist: pylint ; extra == 'lint'
Requires-Dist: pylint-exit ; extra == 'lint'
Requires-Dist: black ==23.12.0 ; extra == 'lint'
Requires-Dist: flake8 ; extra == 'lint'
Provides-Extra: test
Requires-Dist: pytest >=7.3.2 ; extra == 'test'
Requires-Dist: pytest-mock ==3.12.0 ; extra == 'test'
